mloda/community/feature_groups/example/example_a/__init__.py
mloda/community/feature_groups/example/example_a/example_a_feature_group.py
mloda_community_example_a-0.2.6.dist-info/METADATA
mloda_community_example_a-0.2.6.dist-info/WHEEL
mloda_community_example_a-0.2.6.dist-info/top_level.txt
mloda_community_example_a-0.2.6.dist-info/RECORD
