Metadata-Version: 2.4
Name: mloda-community-example-a
Version: 0.2.6
Summary: Example A FeatureGroup extending community example base
Author-email: Tom Kaltofen <info@mloda.ai>
License-Expression: Apache-2.0
Project-URL: Homepage, https://mloda.ai
Project-URL: Repository, https://github.com/mloda-ai/mloda-registry
Requires-Python: >=3.10
Requires-Dist: mloda-community-example>=0.2.0
Provides-Extra: dev
Requires-Dist: mloda-testing; extra == "dev"
Requires-Dist: pytest; extra == "dev"
